dgm_dayabay_dev/__init__.py
dgm_dayabay_dev/bundles/__init__.py
dgm_dayabay_dev/bundles/cross_check_refine_lsnl_data.py
dgm_dayabay_dev/bundles/refine_detector_data.py
dgm_dayabay_dev/bundles/refine_detector_data_v0ae.py
dgm_dayabay_dev/bundles/refine_lsnl_data.py
dgm_dayabay_dev/bundles/refine_reactor_data.py
dgm_dayabay_dev/bundles/refine_reactor_data_v0ae.py
dgm_dayabay_dev/bundles/refine_reactor_data_variable_periods.py
dgm_dayabay_dev/bundles/sync_reactor_detector_data.py
dgm_dayabay_dev/models/__init__.py
dgm_dayabay_dev/models/dayabay_labels.py
dgm_dayabay_dev/models/dayabay_v0.py
dgm_dayabay_dev/models/dayabay_v0_labels.yaml
dgm_dayabay_dev/models/dayabay_v0b.py
dgm_dayabay_dev/models/dayabay_v0b_labels.yaml
dgm_dayabay_dev/models/dayabay_v0c.py
dgm_dayabay_dev/models/dayabay_v0c_labels.yaml
dgm_dayabay_dev/models/dayabay_v0d.py
dgm_dayabay_dev/models/dayabay_v0d_labels.yaml
dgm_dayabay_dev/models/dayabay_v0e.py
dgm_dayabay_dev/models/dayabay_v0e_labels.yaml
dgm_dayabay_dev/models/dayabay_v0f.py
dgm_dayabay_dev/models/dayabay_v0f_labels.yaml
dgm_dayabay_dev/models/dayabay_v1.py
dgm_dayabay_dev/models/dayabay_v1_labels.yaml
dgm_dayabay_dev/models/dayabay_v1a.py
dgm_dayabay_dev/models/dayabay_v1a_distorted.py
dgm_dayabay_dev/models/dayabay_v1a_distorted_labels.yaml
dgm_dayabay_dev/models/dayabay_v1a_labels.yaml
dgm_dayabay_dev/models/dayabay_v1a_neutrino_rate/__init__.py
dgm_dayabay_dev/models/dayabay_v1a_neutrino_rate/model_dayabay.py
dgm_dayabay_dev/models/dayabay_v1a_neutrino_rate/model_dayabay.yaml
dgm_dayabay_dev/models/dayabay_v1a_neutrino_rate/bundles/__init__.py
dgm_dayabay_dev/models/dayabay_v1a_neutrino_rate/bundles/refine_detector_data.py
dgm_dayabay_dev/models/dayabay_v1a_neutrino_rate/bundles/refine_lsnl_data.py
dgm_dayabay_dev/models/dayabay_v1a_neutrino_rate/bundles/refine_neutrino_rate_data.py
dgm_dayabay_dev/models/dayabay_v1a_neutrino_rate/bundles/sync_neutrino_rate_detector_data.py
dgm_dayabay_dev-0.7.1.dist-info/licenses/LICENSE
dgm_dayabay_dev-0.7.1.dist-info/METADATA
dgm_dayabay_dev-0.7.1.dist-info/WHEEL
dgm_dayabay_dev-0.7.1.dist-info/top_level.txt
dgm_dayabay_dev-0.7.1.dist-info/RECORD
