Metadata-Version: 2.4
Name: dgm-dayabay-dev
Version: 0.7.1
Summary: Implementation of the Daya Bay model for dag-modelling framework. Development version.
Author-email: DAGModelling Team <dagflow@jinr.ru>
Maintainer-email: DAGModelling Team <dagflow@jinr.ru>
License-Expression: MIT
Project-URL: Bug Tracker, https://github.com/dagflow-team/dgm-dayabay-dev/issues
Project-URL: DAGModelling Team, https://github.com/dagflow-team
Project-URL: documentation, https://github.com/dagflow-team/dgm-dayabay-dev/wiki
Project-URL: homepage, https://github.com/dagflow-team/dgm-dayabay-dev
Project-URL: repository, https://github.com/dagflow-team/dgm-dayabay-dev
Classifier: Programming Language :: Python :: 3 :: Only
Classifier: Programming Language :: Python :: 3.11
Classifier: Programming Language :: Python :: 3.12
Classifier: Programming Language :: Python :: 3.13
Requires-Python: >=3.11
License-File: LICENSE
Requires-Dist: colorama
Requires-Dist: dgm-fit>=0.2
Requires-Dist: dgm-reactor-neutrino>=0.2.2
Requires-Dist: more-itertools
Requires-Dist: semver
Provides-Extra: test
Requires-Dist: dgm-reactor-neutrino[test]>=0.2.2; extra == "test"
Requires-Dist: ipykernel; extra == "test"
Requires-Dist: ipython; extra == "test"
Requires-Dist: ipywidgets; extra == "test"
Requires-Dist: nbconvert; extra == "test"
Requires-Dist: parameterized; extra == "test"
Dynamic: license-file
